Metadata-Version: 1.1
Name: fixturegen
Version: 0.7
Summary: Fixture generator for fixture module
Home-page: https://github.com/anton44eg/fixturegen
Author: Anton Simernia
Author-email: anton.simernya@gmail.com
License: MIT
Download-URL: https://github.com/anton44eg/fixturegen/archive/0.7.tar.gz
Keywords: fixture,sqlalchemy,testing
Platform: UNKNOWN
Classifier: Environment :: Console
Classifier: Intended Audience :: Developers
Classifier: License :: OSI Approved :: MIT License
Classifier: Topic :: Software Development :: Testing
Classifier: Topic :: Database
